plain_kafka/__init__.py
plain_kafka/consumer.py
plain_kafka/logger.py
plain_kafka/producer.py
plain_kafka-0.0.1.dist-info/WHEEL
plain_kafka-0.0.1.dist-info/METADATA
plain_kafka-0.0.1.dist-info/RECORD
